airas/__init__.py
airas/core/base.py
airas/features/__init__.py
airas/features/analysis/analytic_subgraph/analytic_subgraph.py
airas/features/analysis/analytic_subgraph/input_data.py
airas/features/analysis/analytic_subgraph/nodes/analytic_node.py
airas/features/analysis/analytic_subgraph/prompt/analytic_node_prompt.py
airas/features/create/ai_scientist_create_method_subgraph/ai_scientist_create_method_subgraph.py
airas/features/create/ai_scientist_create_method_subgraph/input_data.py
airas/features/create/ai_scientist_create_method_subgraph/nodes/agent_decision_node.py
airas/features/create/ai_scientist_create_method_subgraph/nodes/generator_node.py
airas/features/create/ai_scientist_create_method_subgraph/nodes/pure_novelty_verification_node.py
airas/features/create/ai_scientist_create_method_subgraph/nodes/refinement_feedback_node.py
airas/features/create/ai_scientist_create_method_subgraph/prompt/PromptManager.py
airas/features/create/ai_scientist_create_method_subgraph/prompt/generator_node_prompt.py
airas/features/create/create_code_subgraph/create_code_subgraph.py
airas/features/create/create_code_subgraph/nodes/push_code_with_devin.py
airas/features/create/create_experimental_design_subgraph/__init__.py
airas/features/create/create_experimental_design_subgraph/create_experimental_design_subgraph.py
airas/features/create/create_experimental_design_subgraph/input_data.py
airas/features/create/create_experimental_design_subgraph/nodes/generate_advantage_criteria.py
airas/features/create/create_experimental_design_subgraph/nodes/generate_experiment_code.py
airas/features/create/create_experimental_design_subgraph/nodes/generate_experiment_details.py
airas/features/create/create_experimental_design_subgraph/prompt/generate_advantage_criteria_prompt.py
airas/features/create/create_experimental_design_subgraph/prompt/generate_experiment_code_prompt.py
airas/features/create/create_experimental_design_subgraph/prompt/generate_experiment_details_prompt.py
airas-0.1.0.dist-info/METADATA
airas-0.1.0.dist-info/WHEEL
airas-0.1.0.dist-info/licenses/LICENSE
airas-0.1.0.dist-info/RECORD
