Metadata-Version: 2.4
Name: airas
Version: 0.1.0
Summary: Add your description here
Project-URL: Homepage, https://www.autores.one/english
Project-URL: Issues, https://github.com/auto-res/airas/issues
Author-email: Toma Tanaka <ulti4929@gmail.com>
License-Expression: MIT
License-File: LICENSE
Keywords: AI,Automation,Research
Requires-Python: <3.13,>=3.10
Requires-Dist: feedparser>=6.0.11
Requires-Dist: google-genai>=1.9.0
Requires-Dist: jinja2>=3.1.4
Requires-Dist: langchain-community>=0.2.15
Requires-Dist: langchain>=0.2.15
Requires-Dist: langgraph>=0.4.8
Requires-Dist: openai>=1.35.13
Requires-Dist: pandas>=2.3.0
Requires-Dist: pymupdf>=1.25.5
Requires-Dist: pypdf>=4.3.1
Requires-Dist: pytz>=2025.2
Requires-Dist: semanticscholar>=0.8.4
Requires-Dist: tenacity>=9.0.0
Requires-Dist: tiktoken>=0.9.0
Requires-Dist: tomli-w>=1.0.0
Requires-Dist: tomli>=2.0.1
Requires-Dist: typing-extensions>=4.12.2
Provides-Extra: mcp
Requires-Dist: asyncio>=3.4.3; extra == 'mcp'
Requires-Dist: mcp[cli]>=1.6.0; extra == 'mcp'
Requires-Dist: python-dotenv>=1.0.1; extra == 'mcp'
